parsers/__init__.py
parsers/parser_factory.py
parsers/json/__init__.py
parsers/json/json_parser.py
parsers/json/source.py
parsers/src/__init__.py
parsers/src/constants.py
parsers/src/serialize_functions.py
parsers/toml/__init__.py
parsers/toml/source.py
parsers/toml/toml_parser.py
parsers/yaml/__init__.py
parsers/yaml/source.py
parsers/yaml/yaml_parser.py
tests/__init__.py
tests/serialize_functions_test.py
tests/test_functions.py
tests/test_objects.py
sdrialization-0.1.0.dist-info/METADATA
sdrialization-0.1.0.dist-info/WHEEL
sdrialization-0.1.0.dist-info/top_level.txt
sdrialization-0.1.0.dist-info/RECORD
