Metadata-Version: 2.1
Name: sdrialization
Version: 0.1.0
Summary: library for python serialization
Home-page: https://github.com/https://github.com/dburackov/PyLabs/lab2
Author: Burackov Dmitry
Author-email: dmburackov@yandex.by
License: UNKNOWN
Platform: UNKNOWN
Classifier: Intended Audience :: Developers
Classifier: Programming Language :: Python
Classifier: Programming Language :: Python :: 3.9
Classifier: Operating System :: OS Independent
